utils/__init__.py
utils/custom_bot.py
utils/custom_cog.py
utils/custom_context.py
utils/database.py
utils/redis.py
utils/checks/__init__.py
utils/checks/custom_checks.py
MyBotUtils-0.1.dist-info/METADATA
MyBotUtils-0.1.dist-info/WHEEL
MyBotUtils-0.1.dist-info/top_level.txt
MyBotUtils-0.1.dist-info/RECORD
